gvcf2bed/__init__.py
gvcf2bed/gvcf2bed.py
gvcf2bed-0.3.1.dist-info/LICENSE
gvcf2bed-0.3.1.dist-info/METADATA
gvcf2bed-0.3.1.dist-info/WHEEL
gvcf2bed-0.3.1.dist-info/entry_points.txt
gvcf2bed-0.3.1.dist-info/top_level.txt
gvcf2bed-0.3.1.dist-info/RECORD
