Metadata-Version: 2.1
Name: gvcf2bed
Version: 0.3.1
Summary: Convert gVCF into BED
Home-page: https://github.com/sndrtj/gvcf2bed
Author: Sander Bollen
Author-email: a.h.b.bollen@lumc.nl
License: MIT
Platform: UNKNOWN
Classifier: Topic :: Scientific/Engineering :: Bio-Informatics
Requires-Dist: pyvcf (==0.6.8)
Requires-Dist: cyvcf2 (>=0.7.4)
